EnergyData/__init__.py
EnergyData/electricpower.py
EnergyData/data/householdpower.csv
test/__init__.py
test/test.py
EnergyData-0.0.2.dist-info/METADATA
EnergyData-0.0.2.dist-info/WHEEL
EnergyData-0.0.2.dist-info/top_level.txt
EnergyData-0.0.2.dist-info/RECORD
